cagecleaner/__init__.py
cagecleaner/classes.py
cagecleaner/dereplicate_assemblies.sh
cagecleaner/download_assemblies.sh
cagecleaner/get_accessions.sh
cagecleaner/main.py
cagecleaner/util.py
cagecleaner-1.4.5.dist-info/licenses/LICENSE
cagecleaner-1.4.5.dist-info/METADATA
cagecleaner-1.4.5.dist-info/WHEEL
cagecleaner-1.4.5.dist-info/entry_points.txt
cagecleaner-1.4.5.dist-info/top_level.txt
cagecleaner-1.4.5.dist-info/RECORD
