Metadata-Version: 2.4
Name: cagecleaner
Version: 1.4.5
Summary: Genomic redundancy removal tool for cblaster hit sets
Author: Lucas De Vrieze
Author-email: lucas.devrieze@kuleuven.be
License: MIT
Classifier: Programming Language :: Python :: 3.12
Classifier: License :: OSI Approved :: MIT License
Classifier: Operating System :: OS Independent
Classifier: Intended Audience :: Science/Research
Classifier: Topic :: Scientific/Engineering :: Bio-Informatics
Requires-Python: >=3.12.0
License-File: LICENSE
Requires-Dist: scipy<=1.14.1
Requires-Dist: biopython
Requires-Dist: cblaster>=1.3.20
Requires-Dist: pandas
Requires-Dist: entrez-direct
Requires-Dist: skder>=1.3.4
Requires-Dist: ncbi-datasets-cli
Requires-Dist: any2fasta
Dynamic: author
Dynamic: author-email
Dynamic: classifier
Dynamic: description
Dynamic: description-content-type
Dynamic: license
Dynamic: license-file
Dynamic: requires-dist
Dynamic: requires-python
Dynamic: summary
